stainlesstest/__init__.py
stainlesstest/_base_client.py
stainlesstest/_client.py
stainlesstest/_compat.py
stainlesstest/_constants.py
stainlesstest/_exceptions.py
stainlesstest/_files.py
stainlesstest/_models.py
stainlesstest/_qs.py
stainlesstest/_resource.py
stainlesstest/_response.py
stainlesstest/_streaming.py
stainlesstest/_types.py
stainlesstest/_version.py
stainlesstest/py.typed
stainlesstest/_utils/__init__.py
stainlesstest/_utils/_logs.py
stainlesstest/_utils/_proxy.py
stainlesstest/_utils/_reflection.py
stainlesstest/_utils/_resources_proxy.py
stainlesstest/_utils/_streams.py
stainlesstest/_utils/_sync.py
stainlesstest/_utils/_transform.py
stainlesstest/_utils/_typing.py
stainlesstest/_utils/_utils.py
stainlesstest/lib/.keep
stainlesstest/resources/__init__.py
stainlesstest/resources/collections.py
stainlesstest/resources/deployments.py
stainlesstest/resources/files.py
stainlesstest/resources/hardware.py
stainlesstest/resources/predictions.py
stainlesstest/resources/trainings.py
stainlesstest/resources/models/__init__.py
stainlesstest/resources/models/models.py
stainlesstest/resources/models/versions.py
stainlesstest/resources/webhooks/__init__.py
stainlesstest/resources/webhooks/default.py
stainlesstest/resources/webhooks/webhooks.py
stainlesstest/types/__init__.py
stainlesstest/types/deployment_create_params.py
stainlesstest/types/deployment_create_prediction_params.py
stainlesstest/types/deployment_list_response.py
stainlesstest/types/deployment_response.py
stainlesstest/types/deployment_update_params.py
stainlesstest/types/file.py
stainlesstest/types/file_create_params.py
stainlesstest/types/file_download_params.py
stainlesstest/types/file_list_response.py
stainlesstest/types/hardware_list_response.py
stainlesstest/types/model_create_params.py
stainlesstest/types/model_create_prediction_params.py
stainlesstest/types/model_get_readme_response.py
stainlesstest/types/model_list_response.py
stainlesstest/types/model_search_params.py
stainlesstest-0.1.0a1.dist-info/METADATA
stainlesstest-0.1.0a1.dist-info/WHEEL
stainlesstest-0.1.0a1.dist-info/licenses/LICENSE
stainlesstest-0.1.0a1.dist-info/RECORD
